<?xml version="1.0" encoding="utf-8" ?>
<dwsync>
<file name="_animated.scss" server="ftp.kairospetro.com.br" local="131722482109217977" remote="131716073400000000" Dst="1" />
<file name="_bordered-pulled.scss" server="ftp.kairospetro.com.br" local="131722482110936907" remote="131716073400000000" Dst="1" />
<file name="_core.scss" server="ftp.kairospetro.com.br" local="131722482114505036" remote="131716073400000000" Dst="1" />
<file name="_fixed-width.scss" server="ftp.kairospetro.com.br" local="131722482117729699" remote="131716073400000000" Dst="1" />
<file name="_larger.scss" server="ftp.kairospetro.com.br" local="131722482121821247" remote="131716073400000000" Dst="1" />
<file name="_icons.scss" server="ftp.kairospetro.com.br" local="131722482123402854" remote="131716073400000000" Dst="1" />
<file name="_list.scss" server="ftp.kairospetro.com.br" local="131722482124809258" remote="131716073400000000" Dst="1" />
<file name="_mixins.scss" server="ftp.kairospetro.com.br" local="131722482130252085" remote="131716073400000000" Dst="1" />
<file name="_path.scss" server="ftp.kairospetro.com.br" local="131722482131660316" remote="131716073400000000" Dst="1" />
<file name="_rotated-flipped.scss" server="ftp.kairospetro.com.br" local="131722482133721625" remote="131716073400000000" Dst="1" />
<file name="_stacked.scss" server="ftp.kairospetro.com.br" local="131722482138745533" remote="131716073400000000" Dst="1" />
<file name="_screen-reader.scss" server="ftp.kairospetro.com.br" local="131722482138901766" remote="131716073400000000" Dst="1" />
<file name="_variables.scss" server="ftp.kairospetro.com.br" local="131722482143917610" remote="131716073400000000" Dst="1" />
<file name="font-awesome.scss" server="ftp.kairospetro.com.br" local="131722482146261952" remote="131716073400000000" Dst="1" />
<file name="font-awesome.css" server="ftp.kairospetro.com.br" local="131722482151149886" remote="131716073400000000" Dst="1" />
</dwsync>